{
    "home-manager": {
        "branch": "master",
        "description": "Manage a user environment using Nix  [maintainer=@rycee] ",
        "homepage": "https://rycee.gitlab.io/home-manager/",
        "owner": "rycee",
        "repo": "home-manager",
        "rev": "6a8444467c83c961e2f5ff64fb4f422e303c98d3",
        "sha256": "1w7cvhfg21slcr9l2grdz9kw4nw2bxmv2r5va6j17s7wcwhlcjwx",
        "type": "tarball",
        "url": "https://github.com/rycee/home-manager/archive/6a8444467c83c961e2f5ff64fb4f422e303c98d3.tar.gz",
        "url_template": "https://github.com/<owner>/<repo>/archive/<rev>.tar.gz"
    },
    "niv": {
        "branch": "master",
        "description": "Easy dependency management for Nix projects",
        "homepage": "https://github.com/nmattia/niv",
        "owner": "nmattia",
        "repo": "niv",
        "rev": "723f0eeb969a730db3c30f977c2b66b9dce9fe4a",
        "sha256": "0016l7230gd2kdh0g2w573r9a2krqb7x4ifcjhhsn4h1bwap7qr0",
        "type": "tarball",
        "url": "https://github.com/nmattia/niv/archive/723f0eeb969a730db3c30f977c2b66b9dce9fe4a.tar.gz",
        "url_template": "https://github.com/<owner>/<repo>/archive/<rev>.tar.gz"
    },
    "nixos-vscode-server": {
        "branch": "master",
        "description": "Visual Studio Code Server support in NixOS",
        "homepage": null,
        "owner": "msteen",
        "repo": "nixos-vscode-server",
        "rev": "1e1358493df6529d4c7bc4cc3066f76fd16d4ae6",
        "sha256": "0sz8njfxn5bw89n6xhlzsbxkafb6qmnszj4qxy2w0hw2mgmjp829",
        "type": "tarball",
        "url": "https://github.com/msteen/nixos-vscode-server/archive/1e1358493df6529d4c7bc4cc3066f76fd16d4ae6.tar.gz",
        "url_template": "https://github.com/<owner>/<repo>/archive/<rev>.tar.gz"
    },
    "nixpkgs": {
        "branch": "nixpkgs-unstable",
        "description": "Nix Packages collection",
        "homepage": "",
        "owner": "NixOS",
        "repo": "nixpkgs",
        "rev": "f0326542989e1bdac955ad6269b334a8da4b0c95",
        "sha256": "1p7vxlwdnhnhg287dp7n890806yi1mmxad0qgfi5f1pr1pgw8pkf",
        "type": "tarball",
        "url": "https://github.com/NixOS/nixpkgs/archive/f0326542989e1bdac955ad6269b334a8da4b0c95.tar.gz",
        "url_template": "https://github.com/<owner>/<repo>/archive/<rev>.tar.gz",
        "version": "21.11"
    },
    "powerlevel10k": {
        "branch": "master",
        "description": "A Zsh theme",
        "homepage": "",
        "owner": "romkatv",
        "repo": "powerlevel10k",
        "rev": "c180a5e040d078eab501a71dc455a8eadc43fd44",
        "sha256": "0rar5jin8jha6rms6x8nh0igk1blsjgmsf5ggqwqdgy10ff8zask",
        "type": "tarball",
        "url": "https://github.com/romkatv/powerlevel10k/archive/c180a5e040d078eab501a71dc455a8eadc43fd44.tar.gz",
        "url_template": "https://github.com/<owner>/<repo>/archive/<rev>.tar.gz",
        "version": "v1.19.0"
    },
    "wally-cli": {
        "branch": "master",
        "description": "Flash your ZSA Keyboard the EZ way.",
        "homepage": null,
        "owner": "zsa",
        "repo": "wally-cli",
        "rev": "b0fafe52cc7fb9d55f2b968d4548c99917c7325c",
        "sha256": "09phq2g51x7rlalzb87aqf48p3j4s7s5jdf5vdf48l9805hi2yha",
        "type": "tarball",
        "url": "https://github.com/zsa/wally-cli/archive/b0fafe52cc7fb9d55f2b968d4548c99917c7325c.tar.gz",
        "url_template": "https://github.com/<owner>/<repo>/archive/<rev>.tar.gz",
        "version": "2.0.1-osx"
    }
}
